{
  "file_metadata": {
    "original_path": "d:\\file_analyze\\by_extension\\txt_files\\31047\\Fabrication\\Recent.txt",
    "filename": "Recent.txt",
    "size_bytes": 130,
    "extension": ".txt",
    "file_type": "text_file",
    "is_binary": false,
    "last_modified": "2012-10-29T16:49:07",
    "export_timestamp": "2025-10-22T15:25:22.016150"
  },
  "analysis": {},
  "content_preview": {
    "text_content": "PH \n000090.apf\n000019.apf\n000042.apf\n000092.apf\n000089.apf\nJY \n000013.apf\n000012.apf\n000011.apf\n000010.apf\n000009.apf\n",
    "preview_length": 118,
    "encoding": "utf-8"
  },
  "error": null
}