{
  "file_metadata": {
    "original_path": "d:\\file_analyze\\by_extension\\dbf_files\\database_files\\31047\\Inst_Welds31047.dbf",
    "filename": "Inst_Welds31047.dbf",
    "size_bytes": 962,
    "extension": ".dbf",
    "file_type": "database",
    "is_binary": true,
    "last_modified": "2012-03-14T10:56:56",
    "export_timestamp": "2025-10-22T15:25:11.139972"
  },
  "analysis": {
    "record_count": 0,
    "field_count": 29,
    "field_names": [
      "CONTROLNO",
      "REVISION",
      "WELDLABEL",
      "WELDFROM",
      "WELDTO",
      "MSWELDCODE",
      "MATGROUP",
      "SIZE_I",
      "SIZE_M",
      "WDESCRIPT",
      "WALL_I",
      "WALL_M",
      "FITTERID",
      "FITDATE",
      "WELDERID",
      "WELDER2ID",
      "WELDDATE",
      "WELDPROC",
      "REMARK",
      "INSP1",
      "INSP2",
      "INSP3",
      "INSP4",
      "INSP5",
      "USERCODE",
      "CLIENTCODE",
      "DIAINCH",
      "FROMMAT",
      "TOMAT"
    ],
    "sample_records": []
  },
  "content_preview": {},
  "error": null
}