{
  "file_metadata": {
    "original_path": "d:\\file_analyze\\by_extension\\apf_files\\fabrication\\BDCC\\Fabrication\\03966A.apf",
    "filename": "03966A.apf",
    "size_bytes": 1364,
    "extension": ".apf",
    "file_type": "fabrication_binary",
    "is_binary": true,
    "last_modified": "2012-02-14T09:25:20",
    "export_timestamp": "2025-10-22T15:25:17.723200"
  },
  "analysis": {},
  "content_preview": {
    "binary_preview": [
      {
        "offset": "00000000",
        "hex": "7e 41 50 46 7e 30 38 32 33 20 64 00 6a 1f 00 00",
        "ascii": "~APF~0823 d.j..."
      },
      {
        "offset": "00000010",
        "hex": "f0 04 00 00 41 50 50 31 20 20 20 20 20 20 20 20",
        "ascii": "....APP1        "
      },
      {
        "offset": "00000020",
        "hex": "20 20 20 20 20 20 20 20 20 20 20 20 20 20 20 20",
        "ascii": "                "
      },
      {
        "offset": "00000030",
        "hex": "20 20 20 20 20 20 20 20 20 20 20 20 20 20 20 20",
        "ascii": "                "
      },
      {
        "offset": "00000040",
        "hex": "20 20 20 20 20 20 20 20 20 20 20 20 20 20 20 20",
        "ascii": "                "
      },
      {
        "offset": "00000050",
        "hex": "20 20 20 20 20 20 20 20 20 20 20 20 20 45 2e 34",
        "ascii": "             E.4"
      },
      {
        "offset": "00000060",
        "hex": "3b 21 46 20 d1 2a 17 ed 85 7c 8d 5c 83 8e 53 24",
        "ascii": ";!F .*...|.\\..S$"
      },
      {
        "offset": "00000070",
        "hex": "e2 7b f0 ac 0e 51 e5 e3 d3 55 19 ec df ca 63 62",
        "ascii": ".{...Q...U....cb"
      },
      {
        "offset": "00000080",
        "hex": "60 2b 81 e2 12 ae 98 60 11 5b b9 4b 5e 95 67 ee",
        "ascii": "`+.....`.[.K^.g."
      },
      {
        "offset": "00000090",
        "hex": "bb 5f 25 a7 76 4c f3 63 d8 91 65 d3 e3 18 a9 e1",
        "ascii": "._%.vL.c..e....."
      },
      {
        "offset": "000000a0",
        "hex": "c4 74 05 37 c7 36 a1 12 7f b2 6b de 23 49 d2 b6",
        "ascii": ".t.7.6....k.#I.."
      },
      {
        "offset": "000000b0",
        "hex": "02 93 59 24 e2 a8 27 4b ee af 36 8a dc 54 24 ce",
        "ascii": "..Y$..'K..6..T$."
      },
      {
        "offset": "000000c0",
        "hex": "cb 03 0f 13 66 09 72 a0 74 8b fd bc 69 4b 94 39",
        "ascii": "....f.r.t...iK.9"
      },
      {
        "offset": "000000d0",
        "hex": "d4 96 74 ad 80 33 41 9d 6f af b3 68 4b 82 9a 6e",
        "ascii": "..t..3A.o..hK..n"
      },
      {
        "offset": "000000e0",
        "hex": "eb a8 84 d5 7c 2f 2b f0 df 18 32 07 a3 bd b4 e0",
        "ascii": "....|/+...2....."
      },
      {
        "offset": "000000f0",
        "hex": "22 4c 6d 6f d9 63 cf 27 93 ae 16 a4 78 96 bf 92",
        "ascii": "\"Lmo.c.'....x..."
      }
    ],
    "preview_size": 256
  },
  "error": null
}