{
  "file_metadata": {
    "original_path": "d:\\file_analyze\\by_extension\\dbf_files\\database_files\\830474\\Fab_XLaborSur2.dbf",
    "filename": "Fab_XLaborSur2.dbf",
    "size_bytes": 194,
    "extension": ".dbf",
    "file_type": "database",
    "is_binary": true,
    "last_modified": "2011-12-02T15:31:50",
    "export_timestamp": "2025-10-22T15:25:11.214570"
  },
  "analysis": {
    "record_count": 0,
    "field_count": 5,
    "field_names": [
      "CONTROLNO",
      "REVISION",
      "XLCODE",
      "XLDESCR",
      "QUANTITY"
    ],
    "sample_records": []
  },
  "content_preview": {},
  "error": null
}